ruamel.windowsregistry-0.1.1-py3.10-nspkg.pth
ruamel/windowsregistry/__init__.py
ruamel.windowsregistry-0.1.1.dist-info/METADATA
ruamel.windowsregistry-0.1.1.dist-info/WHEEL
ruamel.windowsregistry-0.1.1.dist-info/namespace_packages.txt
ruamel.windowsregistry-0.1.1.dist-info/top_level.txt
ruamel.windowsregistry-0.1.1.dist-info/RECORD
