Metadata-Version: 2.1
Name: ruamel.windowsregistry
Version: 0.1.1
Summary: get and set values on windows registry
Home-page: https://sourceforge.net/p/ruamel-windowsregistry/code/ci/default/tree
Author: Anthon van der Neut
Author-email: a.van.der.neut@ruamel.eu
License: Copyright Ruamel bvba 2007-2023
Keywords: pypi statistics
Classifier: Development Status :: 4 - Beta
Classifier: Intended Audience :: Developers
Classifier: License :: Other/Proprietary License
Classifier: Operating System :: OS Independent
Classifier: Programming Language :: Python
Requires-Python: >=3
